eval_hj3415/__init__.py
eval_hj3415/db.py
eval_hj3415/eval.py
eval_hj3415/report.py
eval_hj3415/score.py
eval_hj3415-0.6.4.data/scripts/eval_manager.py
eval_hj3415-0.6.4.dist-info/LICENSE
eval_hj3415-0.6.4.dist-info/METADATA
eval_hj3415-0.6.4.dist-info/WHEEL
eval_hj3415-0.6.4.dist-info/top_level.txt
eval_hj3415-0.6.4.dist-info/RECORD
