Metadata-Version: 2.1
Name: eval-hj3415
Version: 0.6.4
Summary: Evaluating and scoring financial data
Home-page: https://pypi.org/project/eval-hj3415/
Author: hyungjin kim
Author-email: hj3415@gmail.com
License: UNKNOWN
Project-URL: Bug Tracker, https://pypi.org/project/eval-hj3415/
Platform: UNKNOWN
Classifier: Programming Language :: Python :: 3
Classifier: License :: OSI Approved :: MIT License
Classifier: Operating System :: OS Independent
Requires-Python: >=3.6
License-File: LICENSE
Requires-Dist: numpy (>=1.22.1)
Requires-Dist: krx-hj3415 (>=0.3.6)
Requires-Dist: util-hj3415 (>=0.3.7)
Requires-Dist: db-hj3415 (>=1.2.1)
